openapi_client/__init__.py
openapi_client/api_client.py
openapi_client/configuration.py
openapi_client/exceptions.py
openapi_client/rest.py
openapi_client/schemas.py
openapi_client/apis/__init__.py
openapi_client/apis/path_to_api.py
openapi_client/apis/tag_to_api.py
openapi_client/apis/paths/__init__.py
openapi_client/apis/paths/account.py
openapi_client/apis/paths/applications.py
openapi_client/apis/paths/backups.py
openapi_client/apis/paths/backups_backup_id.py
openapi_client/apis/paths/bare_metals.py
openapi_client/apis/paths/bare_metals_baremetal_id.py
openapi_client/apis/paths/bare_metals_baremetal_id_bandwidth.py
openapi_client/apis/paths/bare_metals_baremetal_id_halt.py
openapi_client/apis/paths/bare_metals_baremetal_id_ipv4.py
openapi_client/apis/paths/bare_metals_baremetal_id_ipv6.py
openapi_client/apis/paths/bare_metals_baremetal_id_reboot.py
openapi_client/apis/paths/bare_metals_baremetal_id_reinstall.py
openapi_client/apis/paths/bare_metals_baremetal_id_start.py
openapi_client/apis/paths/bare_metals_baremetal_id_upgrades.py
openapi_client/apis/paths/bare_metals_baremetal_id_user_data.py
openapi_client/apis/paths/bare_metals_baremetal_id_vnc.py
openapi_client/apis/paths/bare_metals_halt.py
openapi_client/apis/paths/bare_metals_reboot.py
openapi_client/apis/paths/bare_metals_start.py
openapi_client/apis/paths/billing_history.py
openapi_client/apis/paths/billing_invoices.py
openapi_client/apis/paths/billing_invoices_invoice_id.py
openapi_client/apis/paths/billing_invoices_invoice_id_items.py
openapi_client/apis/paths/blocks.py
openapi_client/apis/paths/blocks_block_id.py
openapi_client/apis/paths/blocks_block_id_attach.py
openapi_client/apis/paths/blocks_block_id_detach.py
openapi_client/apis/paths/domains.py
openapi_client/apis/paths/domains_dns_domain.py
openapi_client/apis/paths/domains_dns_domain_dnssec.py
openapi_client/apis/paths/domains_dns_domain_records.py
openapi_client/apis/paths/domains_dns_domain_records_record_id.py
vultr_python_client-1.0.1.dist-info/METADATA
vultr_python_client-1.0.1.dist-info/WHEEL
vultr_python_client-1.0.1.dist-info/top_level.txt
vultr_python_client-1.0.1.dist-info/RECORD
